logisim_Verilog/VerilogDM-131-207.v
//TITLE OF THE MINI PROJECT - MINI ATM MACHINE



// NAME: KEERTHANA POLKAMPALLY
//       ARCHANA PRIYADARSHANI SAHOO



//REG NO.: 16CO131
//       : 16CO207 


//ABSTRACT: THE FOLLOWING MINI PROJECT IMPLEMENTS A MINI ATM MACHINE BY TAKING THE INPUT AS A 4 BIT PIN AND IF THE PIN 
//          MATCHES THE PREFED CODE THE MACHINE ALLOWS YOU TO DEPOSIT OR WITHDRAW AND IF THE WRONG PIN IS FED FOR MORE THAN 3 TIMES 
//          THE PROCESS TERMINATES. FOR EVERY SUCCESSFULL TRANSACTION THE BALANCE IS ALSO DISPLAYED.


//FUNCTIONALITIES: 1. CHECKS IF THE PIN IS CORRECT:
//                                                 THE MACHINE VERIFIES IF THE PIN ENTERED BY THE USER MATCHES THE PREFED PIN . THIS FUNCIONALITY 
//                                                 IS VERIFIED BY USING A  4 BIT COMPARATOR. 
//                 2. IF THE WRONG PIN IS ENTERED FOR MORE THAN 3 TIMES:
//                                                                       THIS FUNCTIONALITY IS CHECKED BY USING A 4 BIT PARALLEL ADDER SUBTRACTOR
//                                                                       AND AGAIN A COMPARATOR IS USED TO CHECK IF IT IS MORE THAN 3 OR NOT .IF IT IS THEN IT IS INDICATED BY A SIGNAL.     
//                 3. DEPOSIT OPTION: 
//                                    A SELECT OPTION IS GIVEN IF WE WANT TO OPT FOR DEPOSIT OR WITHDRAWAL .
//                                    DEPOSIT FUNCTIONALITY ALLOWS THE USER TO DEPOSIT AN AMOUNT IN THE MACHINE AND IT REMEMBERS THE AMOUNT USING THE D FLIP FLOPS .
//                                    AND A PARALLEL ADDER SUBTRACTOR AGAIN TAKES CARE OF THE TOTAL BALANCE AND ALSO REMEMBERS FOR FURTHER USE.    
//                 4. WITHDRAWAL OPTION:
//                                      WITHDRAWAL FUNCTIONALITY ALLOWS USER TO WITHDRAW FROM THE MACHINE IF SUFFICIENT BALANCE IS PRESENT IN THE MACHINE .
//                                      ELSE IT GIVES AN ERROR SIGNAL INDICATING NO SUFFICIENT BALANCE. IN CASE OF SUCCESSFULL WITHDRAWAL THE BALANCE IS AGAIN GIVEN AS THE OUTPUT.  



//DESCRIPTION OF CODE: THE CODE CONCENTRATES ON THE ABOVE MENTIONED FUNCTIONALITIES.IT MAINLY HAS 4 COMPONENTS 
//                    1. 4 BIT MAGNITUDE COMPARATOR  2. 4 BIT PARALLEL ADDER SUBTRACTOR 3. MULTIPLEXER 4.D FLIP FLOPS
//                    THE CODE CHECKS IF THE PIN ENTERED BY USER AND PREFED PIN IS EQUAL OR NOT . IF IT IS THEN DEPENDING ON MUX SELECT LINES
//                    DEPOSIT AND WITHDRAWAL OPTION IS CHOSEN AND AGAIN DEPENDING ON THE WITHDRAWAL OR DEPOSIT THE BALANCE IS DISPLAYED AFTER ADDING THE AMOUNT OR SUBTRACTING THE AMOUNT.
//                    IF THE INPUT PIN AND PREFED PASSWORD ARE NOT EQUAL THEN A COUNT IS KEPT TO CHECK IF THE WRONG PIN IS NOT FED FOR MORE THAN 3 TIMES IF IT IS FED FOR 3 MORE THAN 3 TIMES THEN
//                    THE PROCESS IS TERMINATED.      



module main(bal,signal,wd,pin,sel,amt,clk,prefed,dout1,dout,less,greater ,equal);

	input [3:0]pin;       //INPUT PIN BY USER
	input [1:0]sel;       //SELECT LINES FOR MUX TO SELECT WITHDRAWAL OR DEPOSIT OPTION
	input [3:0]amt;       //INPUT AMOUNT TO BE DEPOSITED OR WITHDRAWED FROM MACHINE 
	input clk;            //CLOCK
	input [3:0]prefed;    //PREFED PIN WILL BE GIVEN IN TESTBENCH
	input [3:0]bal;       //BALANCE PRESENT IN THE MACHINE
	output signal;        //SIGNAL INDICATING IF WRONG INPUTS ARE 3 OR NOT  
	output wd;            //WITHDRAW SIGNAL INDICATING IF THE AMOUNT WE WANT TO WITHDRAW IS NOT POSSIBLE 
	output [3:0]dout;     // FINAL BALANCE TO BE OUTPUTTED
	output [3:0]dout1; 
	 output less ,greater,equal;

comparator a1(pin,prefed,less,equal,greater);         // COMPARING IF THE INPUT GIVEN BY THE USER IS SIMILAR TO THE PREFED PIN

adder_subtractor_4bit a2(4'b0000,4'b0001,1'b0,dout);  // A COUNTER TO CHECK IF THE NUMBER OF WRONG INPUTS IS LESS THEN 3

assign signal=4'b0001;
assign wd=1'b0;

adder_subtractor_4bit a3(amt,bal,1'b0,dout1);         // DEPOSIT AND WITHDRAWAL OF THE AMOUNT GIVEN BY THE USER


endmodule

module comparator(
    input [3:0]Data_in_A,               //input A
    input [3:0]Data_in_B,               //input B
    output less,                        //high when A is less than B
    output equal,                       //high when A is equal to B
     output greater                     //high when A is greater than B    
    );

     //Internal variables
     reg less;
     reg equal;
     reg greater;

    //When the inputs and A or B are changed execute this block
    always @(Data_in_A or Data_in_B)
     begin
        if(Data_in_A > Data_in_B)   begin              //check if A is bigger than B.
            less = 0;
            equal = 0;
            greater = 1;    end
        else if(Data_in_A == Data_in_B) begin          //Check if A is equal to B
            less = 0;
            equal = 1;
            greater = 0;    end
        else    begin                                 //Otherwise - check for A less than B.
            less = 1;
            equal = 0;
            greater =0;
        end 
    end
endmodule






module adder_subtractor_4bit ( a ,b , select ,dout );         // PARALLEL ADDER SUBTRACTOR

	output [3:0] dout ;

	input [3:0] a ;                                       // INPUT 1
	input [3:0] b ;                                       // INPUT 2
	input select ;                                        // SELECT LINE TO DECIDE IF THE COMPONET WORKS AS ADDER OR A SUBTRACTOR

	wire [2:0]s;
	wire [3:0]l;

	assign l = b ^ {select,select,select,select};

	full_adder u0 (a[0],l[0],select,dout[0],s[0]); // 4 FULL ADDERS PERFORMING THE OPERATION ON THE RESPECTIVE BITS INCLUDING THE CARRY BIT 
	full_adder u1 (a[1],l[1],s[0],dout[1],s[1]);
	full_adder u2 (a[2],l[2],s[1],dout[2],s[2]);
	full_adder u3 (a[3],l[3],s[2],dout[3],);

endmodule





module full_adder (a ,b ,c ,dout ,carry );     // MODULE FOR FULL ADDER WHICH IS BEING USED FOR MAKING 4-BIT PARRALEL ADDER SUBTRACTOR

	output dout ;
	output carry ;

	input a ;
	input b ;
	input c ;
	   
	assign dout = a ^ b ^ c;               // SUM 
	assign carry = (a&b) | (b&c) | (c&a);  // FINAL CARRY 

endmodule


module mux4_1(I0,I1,I2,I3,s2,s1,en,y);

	input I0,I1,I2,I3,s2,s1,en;  // THE MUX SELECTS FROM THE OPTIONS WHTHER IT HAS TO DEPOSIT OR WITHDRAW ACCORDING TO THE USER INPUT

	output y;

	wire y1,y2,y3,y4;

	assign y1 = ((~s2) & (~s1) & en & I0);
	assign y2 = ((~s2) & (s1) & en & I1);
	assign y3 = (s2 & (~s1) & en & I2);
	assign y4 = (s2 & s1 & en & I3);
	assign y = y1 | y2 | y3 | y4;

endmodule





module d(q,q_bar,d,clk);            // D FLIPFLOPS ARE THE MEMORY ELEMENTS WHICH PERFORM THE FUNCTION OF RETAINING THE BALANCE 

	output q,q_bar;

	input d;

	input clk;

	reg q;
	reg q_bar;

	always @(posedge clk)        //	POSITIVE EDGE TRIGGERED
	begin
	q=d;
	q_bar = ~d;
	end
endmodule

logisim_Verilog/Verilog-131-207.v
// TITLE OF THE MINI PROJECT - MINI ATM MACHINE


// NAME: KEERTHANA POLKAMPALLY
//       ARCHANA PRIYADARSHANI SAHOO

// REG NO.: 16CO131
//       : 16CO207 


//ABSTRACT: THE FOLLOWING MINI PROJECT IMPLEMENTS A MINI ATM MACHINE BY TAKING THE INPUT AS A 4 BIT PIN AND IF THE PIN 
//          MATCHES THE PREFED CODE THE MACHINE ALLOWS YOU TO DEPOSIT OR WITHDRAW AND IF THE WRONG PIN IS FED FOR MORE THAN 3 TIMES 
//          THE PROCESS TERMINATES. FOR EVERY SUCCESSFULL TRANSACTION THE BALANCE IS ALSO DISPLAYED.


//FUNCTIONALITIES: 1. CHECKS IF THE PIN IS CORRECT:
//                                                 THE MACHINE VERIFIES IF THE PIN ENTERED BY THE USER MATCHES THE PREFED PIN . THIS FUNCIONALITY 
//                                                 IS VERIFIED BY USING A  4 BIT COMPARATOR. 
//                 2. IF THE WRONG PIN IS ENTERED FOR MORE THAN 3 TIMES:
//                                                                       THIS FUNCTIONALITY IS CHECKED BY USING A 4 BIT PARALLEL ADDER SUBTRACTOR
//                                                                       AND AGAIN A COMPARATOR IS USED TO CHECK IF IT IS MORE THAN 3 OR NOT .IF IT IS THEN IT IS INDICATED BY A SIGNAL.     
//                 3. DEPOSIT OPTION: 
//                                    A SELECT OPTION IS GIVEN IF WE WANT TO OPT FOR DEPOSIT OR WITHDRAWAL .
//                                    DEPOSIT FUNCTIONALITY ALLOWS THE USER TO DEPOSIT AN AMOUNT IN THE MACHINE AND IT REMEMBERS THE AMOUNT USING THE D FLIP FLOPS .
//                                    AND A PARALLEL ADDER SUBTRACTOR AGAIN TAKES CARE OF THE TOTAL BALANCE AND ALSO REMEMBERS FOR FURTHER USE.    
//                 4. WITHDRAWAL OPTION:
//                                      WITHDRAWAL FUNCTIONALITY ALLOWS USER TO WITHDRAW FROM THE MACHINE IF SUFFICIENT BALANCE IS PRESENT IN THE MACHINE .
//                                      ELSE IT GIVES AN ERROR SIGNAL INDICATING NO SUFFICIENT BALANCE. IN CASE OF SUCCESSFULL WITHDRAWAL THE BALANCE IS AGAIN GIVEN AS THE OUTPUT.  



//DESCRIPTION OF CODE: REGISTERS AND WIRES ARE DECLARED
//                     THE REQUIRED VARIABLES ARE INITIALIZED.
//                     INPUTS ARE GIVEN ACCORDING TO THE TIMING SIGNALS AND THE CHANGE IN CLOCK PULSE WITH TIME IS ALSO PROVIDED.
//                     FINISH TIME IS GIVEN AND THE OUTPUT IS DISPLAYED ON THE SCREEN.      




//   TESTBENCH


`timescale 1ns/1ps
module test;

	wire [3:0]dout1;                 // THE AVAILABLE BALANCE
	wire signal;                     //SIGNAL INDICATING IF WRONG INPUTS ARE 3 OR NOT  
	wire wd;                         //WITHDRAW SIGNAL INDICATING IF THE AMOUNT WE WANT TO WITHDRAW IS NOT POSSIBLE 
	wire [3:0]dout;                  // FINAL BALANCE TO BE OUTPUT
	wire less ,greater,equal;        // TO COMPARE THE INPUT PIN WITH THE PREFED PIN

	reg [3:0]pin;                    // INPUT PIN GIVEN BY THE USER
	reg [3:0]amt;                    //INPUT AMOUNT TO BE DEPOSITED OR WITHDRAWED FROM MACHINE 
	reg [1:0]sel;                    //SELECT LINES FOR MUX TO SELECT WITHDRAWAL OR DEPOSIT OPTION
	reg [3:0]bal;                    //BALANCE PRESENT IN THE MACHINE
	reg clk;                         //CLOCK
	reg [3:0]prefed;                 // THE PREFED PIN

 main uut(bal,signal,wd,pin,sel,amt,clk,prefed,dout1,dout,less,greater,equal);

 initial begin
    
    $dumpfile("VerilogDM-131-207.vcd");                // FOR CREATION OF THE GTKWAVE
    //$dumpfile("VerilogBM-131-207.vcd");
    $dumpvars(0,test); 
 
	  clk = 0;                                     // INITIALIZATION OF THE VALUES
	  amt = 4'b0000;
	  bal = 4'b0000;
	  sel = 2'b00;
	  prefed = 4'b0110;
	 

	 
	 #2 pin = 4'b0110;
	 #2 pin = 4'b0011;
	 #2 pin = 4'b0110;
	 #2 pin = 4'b0011;
	 #2 pin = 4'b0110;
	 #2 pin = 4'b0110;
	 #2 pin = 4'b0011;
	 #2 pin = 4'b0110;

	 #2 amt = 4'b0000; 
	 #2 amt = 4'b0001;
	 #2 amt = 4'b0010;
	 #2 amt = 4'b0011;
	 #2 amt = 4'b0001;    
	 #2 amt = 4'b0001; 
	 #2 amt = 4'b0011;
	 #2 amt = 4'b0001;
	 #2 amt = 4'b0001;
	 #2 amt = 4'b0001;    
	 
	 #2 sel = 2'b00;
	 #2 sel = 2'b00;
	 #2 sel = 2'b01;
	 #2 sel = 2'b00;
	 #2 sel = 2'b01;
	 #2 sel = 2'b00;
	 #2 sel = 2'b01;
	 #2 sel = 2'b00;
	 #2 sel = 2'b00; 
	  
	 #2 bal = 4'b0000;
	 #2 bal = 4'b0000;
	 #2 bal = 4'b0001;
	 #2 bal = 4'b0011;
	 #2 bal = 4'b0110;
	 #2 bal = 4'b0111;
	 #2 bal = 4'b1000;
	 #2 bal = 4'b1011;
	 #2 bal = 4'b1100;
	 #2 bal = 4'b1101;    
	   
	 
end
 


always  #1 clk = ~clk;                        //CLOCK PULSE IS CHANGED EVERY ONE SECOND
 

 
initial #100 $finish;                         //THE PROCESS TERMINATES AFTER 100 SECONDS
   
initial begin                                 // OUTPUT MESSAGE 

                            
    $monitor("time = %d clk = %b pin = %b prefed = %b amt = %b sel = %b  bal = %b signal = %b wd = %d ",$time,clk,pin,prefed,amt,sel,dout1,signal,wd);


end

endmodule

logisim_Verilog/VerilogDM-131-207.vcd
$date
	Fri Nov 10 22:09:26 2017
$end
$version
	Icarus Verilog
$end
$timescale
	1ps
$end
$scope module test $end
$var wire 1 ! wd $end
$var wire 1 " signal $end
$var wire 1 # less $end
$var wire 1 $ greater $end
$var wire 1 % equal $end
$var wire 4 & dout1 [3:0] $end
$var wire 4 ' dout [3:0] $end
$var reg 4 ( amt [3:0] $end
$var reg 4 ) bal [3:0] $end
$var reg 1 * clk $end
$var reg 4 + pin [3:0] $end
$var reg 4 , prefed [3:0] $end
$var reg 2 - sel [1:0] $end
$scope module uut $end
$var wire 4 . amt [3:0] $end
$var wire 4 / bal [3:0] $end
$var wire 1 * clk $end
$var wire 4 0 pin [3:0] $end
$var wire 4 1 prefed [3:0] $end
$var wire 2 2 sel [1:0] $end
$var reg 4 3 dout [3:0] $end
$var reg 4 4 dout1 [3:0] $end
$var reg 1 % equal $end
$var reg 1 $ greater $end
$var reg 1 # less $end
$var reg 1 " signal $end
$var reg 1 ! wd $end
$upscope $end
$upscope $end
$enddefinitions $end
#0
$dumpvars
bx 4
bx 3
b0 2
b110 1
bx 0
b0 /
b0 .
b0 -
b110 ,
bx +
0*
b0 )
b0 (
bx '
bx &
x%
x$
x#
x"
x!
$end
#1000
1*
#2000
0*
b110 +
b110 0
#3000
b0 &
b0 4
1*
#4000
0*
b11 +
b11 0
#5000
1"
b1 '
b1 3
1*
#6000
0*
b110 +
b110 0
#7000
1*
#8000
0*
b11 +
b11 0
#9000
1*
#10000
0*
b110 +
b110 0
#11000
1*
#12000
0*
#13000
1*
#14000
0*
b11 +
b11 0
#15000
1*
#16000
0*
b110 +
b110 0
#17000
1*
#18000
0*
#19000
1*
#20000
0*
b1 (
b1 .
#21000
b1 &
b1 4
1*
#22000
0*
b10 (
b10 .
#23000
b10 &
b10 4
1*
#24000
0*
b11 (
b11 .
#25000
b11 &
b11 4
1*
#26000
0*
b1 (
b1 .
#27000
b1 &
b1 4
1*
#28000
0*
#29000
1*
#30000
0*
b11 (
b11 .
#31000
b11 &
b11 4
1*
#32000
0*
b1 (
b1 .
#33000
b1 &
b1 4
1*
#34000
0*
#35000
1*
#36000
0*
#37000
1*
#38000
0*
#39000
1*
#40000
0*
#41000
1*
#42000
0*
b1 -
b1 2
#43000
0!
1*
#44000
0*
b0 -
b0 2
#45000
1*
#46000
0*
b1 -
b1 2
#47000
1*
#48000
0*
b0 -
b0 2
#49000
1*
#50000
0*
b1 -
b1 2
#51000
1*
#52000
0*
b0 -
b0 2
#53000
1*
#54000
0*
#55000
1*
#56000
0*
#57000
1*
#58000
0*
#59000
1*
#60000
0*
b1 )
b1 /
#61000
b10 &
b10 4
1*
#62000
0*
b11 )
b11 /
#63000
b100 &
b100 4
1*
#64000
0*
b110 )
b110 /
#65000
b111 &
b111 4
1*
#66000
0*
b111 )
b111 /
#67000
b1000 &
b1000 4
1*
#68000
0*
b1000 )
b1000 /
#69000
b1001 &
b1001 4
1*
#70000
0*
b1011 )
b1011 /
#71000
b1100 &
b1100 4
1*
#72000
0*
b1100 )
b1100 /
#73000
b1101 &
b1101 4
1*
#74000
0*
b1101 )
b1101 /
#75000
b1110 &
b1110 4
1*
